fetchDBconn/__init__.py
fetchDBconn/fetchDBconn.py
fetchDBconn-0.1.0.dist-info/LICENSE
fetchDBconn-0.1.0.dist-info/LICENSE.txt
fetchDBconn-0.1.0.dist-info/METADATA
fetchDBconn-0.1.0.dist-info/WHEEL
fetchDBconn-0.1.0.dist-info/top_level.txt
fetchDBconn-0.1.0.dist-info/RECORD
