Metadata-Version: 2.1
Name: fetchDBconn
Version: 0.1.0
Summary: Fetch db conn details from AWS secret manager
Home-page: https://github.com/krishna-pydimarri/dbconn
Author: Krishna Sailesh Pydimarri
Author-email: krishnasailesh93@gmail.com
License: UNKNOWN
Platform: UNKNOWN
Classifier: Programming Language :: Python :: 3
Classifier: License :: OSI Approved :: MIT License
Classifier: Operating System :: OS Independent
